serverless_discovery_sdk/DiscoverySdk.py
serverless_discovery_sdk/DiscoveryServiceApi.py
serverless_discovery_sdk/__init__.py
serverless_discovery_sdk-0.0.5.dist-info/METADATA
serverless_discovery_sdk-0.0.5.dist-info/RECORD
serverless_discovery_sdk-0.0.5.dist-info/WHEEL
serverless_discovery_sdk-0.0.5.dist-info/top_level.txt
