Metadata-Version: 2.1
Name: serverless-discovery-sdk
Version: 0.0.5
Summary: Serverless Service Discovery SDK
Home-page: https://github.com/adastradev/serverless-discovery-sdk-python
Author: Andrew Regier
Author-email: aregier@regiernet.com
License: UNKNOWN
Platform: UNKNOWN
Classifier: Programming Language :: Python :: 3
Classifier: License :: OSI Approved :: MIT License
Classifier: Operating System :: OS Independent
